MANIFEST.in
README.rst
VERSION
requirements.txt
setup.cfg
setup.py
sphinxcontrib/__init__.py
sphinxcontrib/book/__init__.py
sphinxcontrib/book/config.py
sphinxcontrib/book/_extensions/__init__.py
sphinxcontrib/book/_extensions/toggle_code_block.py
sphinxcontrib_book.egg-info/PKG-INFO
sphinxcontrib_book.egg-info/SOURCES.txt
sphinxcontrib_book.egg-info/dependency_links.txt
sphinxcontrib_book.egg-info/namespace_packages.txt
sphinxcontrib_book.egg-info/not-zip-safe
sphinxcontrib_book.egg-info/requires.txt
sphinxcontrib_book.egg-info/top_level.txt