Metadata-Version: 1.1
Name: sphinxcontrib-book
Version: 0.9.3
Summary: sphinxcontrib-book
